{
  "status": "family_within_latency_budget_but_loses_baseline",
  "comparison_bucket": "pade_m=1,pade_n=2,max_order=3,interval=3,pade_only_single_step=true,pade_denom_threshold=0.001,total_images=100,batch_size=2,seed=42,cfg_scale=1.5,num_sampling_steps=250",
  "bucket_best": false,
  "pade_target_file": "/home/yjs/TaylorSeer/TaylorSeer-DiT/taylor_utils/__init__.py",
  "pade_code_sha256": "7f114ec98c17534746977c71b75e95be6680841bcec32abf0d6fac2f5606e431",
  "pade_snapshot_file": "/home/yjs/autoresearch/runs/20260410-014501-m1-n2-k3-i3/pade_target_snapshot.py",
  "lpips": 0.06147932963212952,
  "relative_l1": 1.0569823437994759,
  "ssim": 0.899468368493685,
  "rmse": 5.597475941730112,
  "psnr": 28.531419041271512,
  "cosine": 0.9921475737582299,
  "sample_seconds": 342.06419587135315,
  "eval_seconds": 14.018913507461548,
  "total_seconds": 356.0837905406952,
  "latency_baseline_timestamp": "20260329-171615",
  "latency_baseline_sample_seconds": 751.529,
  "sample_seconds_budget": 789.10545,
  "sample_seconds_ratio": 0.4551576797054447,
  "latency_within_budget": true,
  "pade_m": 1,
  "pade_n": 2,
  "max_order": 3,
  "interval": 3,
  "enable_pade": true,
  "pade_only_single_step": true,
  "pade_denom_threshold": 0.001,
  "total_images": 100,
  "batch_size": 2,
  "seed": 42,
  "cfg_scale": 1.5,
  "num_sampling_steps": 250,
  "paired_control_scope": "standing_pure_taylor",
  "paired_control_timestamp": "20260329-171615",
  "paired_outcome": "worse_than_paired_control",
  "paired_control_lpips": 0.061478,
  "paired_control_relative_l1": 1.056978,
  "paired_control_ssim": 0.899468,
  "paired_control_rmse": 5.59743,
  "paired_delta_lpips": 1.329632129523639e-06,
  "paired_delta_relative_l1": 4.3437994758921405e-06,
  "paired_delta_ssim": 3.6849368501012947e-07,
  "paired_delta_rmse": 4.594173011174263e-05,
  "approx_total_steps": 50,
  "pade_steps": 50,
  "taylor_steps": 0,
  "mixed_steps": 0,
  "pade_calls": 50,
  "taylor_calls": 0,
  "pade_step_ratio": 1.0,
  "pade_call_ratio": 1.0,
  "artifact_dir": "/home/yjs/autoresearch/runs/20260410-014501-m1-n2-k3-i3",
  "description": "candidate: linear-and-curvature-aligned sign-aware 62.40234375%-cubic blend on last-layer MLP for final three steps under interval-3 latency budget"
}