{
  "status": "family_beats_baseline_but_too_slow",
  "comparison_bucket": "pade_m=1,pade_n=2,max_order=3,interval=3,pade_only_single_step=true,pade_denom_threshold=0.001,total_images=100,batch_size=2,seed=42,cfg_scale=1.5,num_sampling_steps=250",
  "bucket_best": false,
  "pade_target_file": "/home/yjs/TaylorSeer/TaylorSeer-DiT/taylor_utils/__init__.py",
  "pade_code_sha256": "429a48681325ecdf9d8f49b7eb6fc38592c55c8021ab832b550ec62263e5a226",
  "pade_snapshot_file": "/home/yjs/autoresearch/runs/20260409-162541-m1-n2-k3-i3/pade_target_snapshot.py",
  "lpips": 0.06146288878982887,
  "relative_l1": 1.056914302397874,
  "ssim": 0.8994842140889523,
  "rmse": 5.598140336401437,
  "psnr": 28.531402506061312,
  "cosine": 0.992158759377733,
  "sample_seconds": 1441.1361343860626,
  "eval_seconds": 14.69089961051941,
  "total_seconds": 1455.8280153274536,
  "latency_baseline_timestamp": "20260329-171615",
  "latency_baseline_sample_seconds": 751.529,
  "sample_seconds_budget": 789.10545,
  "sample_seconds_ratio": 1.9176054874609798,
  "latency_within_budget": false,
  "pade_m": 1,
  "pade_n": 2,
  "max_order": 3,
  "interval": 3,
  "enable_pade": true,
  "pade_only_single_step": true,
  "pade_denom_threshold": 0.001,
  "total_images": 100,
  "batch_size": 2,
  "seed": 42,
  "cfg_scale": 1.5,
  "num_sampling_steps": 250,
  "paired_control_scope": "standing_pure_taylor",
  "paired_control_timestamp": "20260329-171615",
  "paired_outcome": "better_than_paired_control",
  "paired_control_lpips": 0.061478,
  "paired_control_relative_l1": 1.056978,
  "paired_control_ssim": 0.899468,
  "paired_control_rmse": 5.59743,
  "paired_delta_lpips": -1.5111210171128708e-05,
  "paired_delta_relative_l1": -6.36976021259894e-05,
  "paired_delta_ssim": 1.621408895224885e-05,
  "paired_delta_rmse": 0.0007103364014371394,
  "approx_total_steps": 8300,
  "pade_steps": 4050,
  "taylor_steps": 4250,
  "mixed_steps": 0,
  "pade_calls": 226800,
  "taylor_calls": 238000,
  "pade_step_ratio": 0.4879518072289157,
  "pade_call_ratio": 0.4879518072289157,
  "artifact_dir": "/home/yjs/autoresearch/runs/20260409-162541-m1-n2-k3-i3",
  "description": "candidate: sign-aware soft clip from Taylor-3 toward Taylor-2 in amplifying cubic region"
}